plaidcloud/config/__init__.py
plaidcloud/config/config.py
plaidcloud/config/rabbitmq.py
plaidcloud/config/redis.py
plaidcloud_config-0.1.46.dist-info/METADATA
plaidcloud_config-0.1.46.dist-info/WHEEL
plaidcloud_config-0.1.46.dist-info/top_level.txt
plaidcloud_config-0.1.46.dist-info/RECORD
