Metadata-Version: 2.4
Name: plaidcloud-config
Version: 0.1.46
Summary: Basic utility to parse a configuration for PlaidCloud application stack.
Author-email: Garrett Bates <garrett.bates@tartansolutions.com>, Michael Rea <mike@plaidcloud.com>, Paul Morel <paul@plaidcloud.com>
Maintainer-email: Michael Rea <mike@plaidcloud.com>, Paul Morel <paul@plaidcloud.com>, Pat Buxton <pat@plaidcloud.com>, Charlie Laymon <charlie@plaidcloud.com>, Simon Moscrop <simon@plaidcloud.com>
License-Expression: Apache-2.0
Project-URL: Homepage, https://plaidcloud.com
Project-URL: Documentation, https://docs.plaidcloud.com
Project-URL: Repository, https://github.com/PlaidCloud/plaidcloud-config.git
Project-URL: Issues, https://github.com/PlaidCloud/plaidcloud-config/issues
Keywords: plaidcloud,configuration,config
Classifier: Development Status :: 5 - Production/Stable
Classifier: Programming Language :: Python :: 3
Classifier: Programming Language :: Python :: 3.10
Classifier: Programming Language :: Python :: 3.11
Classifier: Programming Language :: Python :: 3.12
Requires-Python: >=3.10
Requires-Dist: pyyaml
